bfo_torch/__init__.py
bfo_torch/optimizer.py
bfo_torch/utils.py
bfo_torch/benchmarks/__init__.py
bfo_torch-0.2.2.dist-info/licenses/LICENSE
bfo_torch-0.2.2.dist-info/METADATA
bfo_torch-0.2.2.dist-info/WHEEL
bfo_torch-0.2.2.dist-info/top_level.txt
bfo_torch-0.2.2.dist-info/RECORD
