Metadata-Version: 2.4
Name: bfo-torch
Version: 0.2.2
Summary: PyTorch Bacterial Foraging Optimizer - Biologically-inspired derivative-free optimization for machine learning and scientific computing
Author: Brett G. Bonner
License: MIT License
Project-URL: Homepage, https://github.com/bbopen/torch_bfo
Project-URL: Documentation, https://github.com/bbopen/torch_bfo/wiki
Project-URL: Repository, https://github.com/bbopen/torch_bfo
Project-URL: Bug Tracker, https://github.com/bbopen/torch_bfo/issues
Keywords: pytorch,optimizer,bfo,bacterial,foraging,optimization,machine,learning,deep,learning
Classifier: Development Status :: 5 - Production/Stable
Classifier: Intended Audience :: Developers
Classifier: Intended Audience :: Science/Research
Classifier: Operating System :: OS Independent
Classifier: Programming Language :: Python :: 3
Classifier: Programming Language :: Python :: 3 :: Only
Classifier: Programming Language :: Python :: 3.8
Classifier: Programming Language :: Python :: 3.9
Classifier: Programming Language :: Python :: 3.10
Classifier: Programming Language :: Python :: 3.11
Classifier: Programming Language :: Python :: 3.12
Classifier: Environment :: GPU
Classifier: Topic :: Scientific/Engineering :: Artificial Intelligence
Classifier: Topic :: Scientific/Engineering :: Mathematics
Classifier: Topic :: Software Development :: Libraries :: Python Modules
Requires-Python: >=3.8
License-File: LICENSE
Requires-Dist: torch>=1.9.0
Requires-Dist: numpy>=1.19.0
Provides-Extra: dev
Requires-Dist: pytest>=6.0.0; extra == "dev"
Requires-Dist: pytest-cov>=2.10.0; extra == "dev"
Requires-Dist: ruff>=0.1.0; extra == "dev"
Requires-Dist: mypy>=0.800; extra == "dev"
Provides-Extra: examples
Requires-Dist: matplotlib>=3.3.0; extra == "examples"
Requires-Dist: scikit-learn>=0.24.0; extra == "examples"
Requires-Dist: torchvision>=0.10.0; extra == "examples"
Provides-Extra: docs
Requires-Dist: sphinx>=4.0.0; extra == "docs"
Requires-Dist: sphinx-rtd-theme>=0.5.0; extra == "docs"
Requires-Dist: myst-parser>=0.15.0; extra == "docs"
Dynamic: license-file
